polars_whichlang-0.1.1.dist-info/METADATA
polars_whichlang-0.1.1.dist-info/WHEEL
polars_whichlang-0.1.1.dist-info/licenses/LICENSE
polars_whichlang/__init__.py
polars_whichlang/_internal.abi3.so
polars_whichlang/py.typed
polars_whichlang-0.1.1.dist-info/RECORD
